<?xml version="1.0" encoding="UTF-8"?>
<tv>
  <programme start="2025-05-14T00:30:00Z" channel="CF Universidad de Chile vs Carabobo FC">
    <title>CF Universidad de Chile vs Carabobo FC</title>
    <desc>Copa Libertadores</desc>
  </programme>
  <programme start="2025-05-14T00:30:00Z" channel="CS Cristal vs Club Cerro Porteño">
    <title>CS Cristal vs Club Cerro Porteño</title>
    <desc>Copa Libertadores</desc>
  </programme>
  <programme start="2025-05-14T00:30:00Z" channel="Fortaleza EC vs CA Bucaramanga">
    <title>Fortaleza EC vs CA Bucaramanga</title>
    <desc>Copa Libertadores</desc>
  </programme>
  <programme start="2025-05-14T17:00:00Z" channel="Deportivo Alavés vs Valencia CF">
    <title>Deportivo Alavés vs Valencia CF</title>
    <desc>Primera Division</desc>
  </programme>
  <programme start="2025-05-14T17:00:00Z" channel="Villarreal CF vs CD Leganés">
    <title>Villarreal CF vs CD Leganés</title>
    <desc>Primera Division</desc>
  </programme>
  <programme start="2025-05-14T18:00:00Z" channel="NEC vs NAC Breda">
    <title>NEC vs NAC Breda</title>
    <desc>Eredivisie</desc>
  </programme>
  <programme start="2025-05-14T18:00:00Z" channel="FC Groningen vs AFC Ajax">
    <title>FC Groningen vs AFC Ajax</title>
    <desc>Eredivisie</desc>
  </programme>
  <programme start="2025-05-14T18:00:00Z" channel="FC Twente '65 vs AZ">
    <title>FC Twente '65 vs AZ</title>
    <desc>Eredivisie</desc>
  </programme>
  <programme start="2025-05-14T18:00:00Z" channel="Feyenoord Rotterdam vs RKC Waalwijk">
    <title>Feyenoord Rotterdam vs RKC Waalwijk</title>
    <desc>Eredivisie</desc>
  </programme>
  <programme start="2025-05-14T18:00:00Z" channel="Almere City FC vs Fortuna Sittard">
    <title>Almere City FC vs Fortuna Sittard</title>
    <desc>Eredivisie</desc>
  </programme>
  <programme start="2025-05-14T18:00:00Z" channel="PSV vs Heracles Almelo">
    <title>PSV vs Heracles Almelo</title>
    <desc>Eredivisie</desc>
  </programme>
  <programme start="2025-05-14T18:00:00Z" channel="FC Utrecht vs Sparta Rotterdam">
    <title>FC Utrecht vs Sparta Rotterdam</title>
    <desc>Eredivisie</desc>
  </programme>
  <programme start="2025-05-14T18:00:00Z" channel="Willem II Tilburg vs PEC Zwolle">
    <title>Willem II Tilburg vs PEC Zwolle</title>
    <desc>Eredivisie</desc>
  </programme>
  <programme start="2025-05-14T18:00:00Z" channel="Go Ahead Eagles vs SC Heerenveen">
    <title>Go Ahead Eagles vs SC Heerenveen</title>
    <desc>Eredivisie</desc>
  </programme>
  <programme start="2025-05-14T19:30:00Z" channel="Real Madrid CF vs RCD Mallorca">
    <title>Real Madrid CF vs RCD Mallorca</title>
    <desc>Primera Division</desc>
  </programme>
  <programme start="2025-05-14T22:00:00Z" channel="CA Peñarol vs Olimpia Asuncion">
    <title>CA Peñarol vs Olimpia Asuncion</title>
    <desc>Copa Libertadores</desc>
  </programme>
  <programme start="2025-05-14T22:00:00Z" channel="CDC Atlético Nacional vs EC Bahia">
    <title>CDC Atlético Nacional vs EC Bahia</title>
    <desc>Copa Libertadores</desc>
  </programme>
  <programme start="2025-05-14T22:00:00Z" channel="CA Vélez Sarsfield vs San Antonio Bulo Bulo">
    <title>CA Vélez Sarsfield vs San Antonio Bulo Bulo</title>
    <desc>Copa Libertadores</desc>
  </programme>
</tv>
